codeconsolidator/__init__.py
codeconsolidator/app.py
codeconsolidator-0.1.8.dist-info/METADATA
codeconsolidator-0.1.8.dist-info/WHEEL
codeconsolidator-0.1.8.dist-info/entry_points.txt
codeconsolidator-0.1.8.dist-info/top_level.txt
codeconsolidator-0.1.8.dist-info/RECORD
