Metadata-Version: 2.1
Name: codeconsolidator
Version: 0.1.8
Summary: Consolidates and analyzes codebases for insights.
Home-page: https://github.com/kamilstanuch/codeconsolidator
Author: Kamil Stanuch
Keywords: code analysis,codebase,consolidation,visualization
Classifier: Development Status :: 3 - Alpha
Classifier: Intended Audience :: Developers
Classifier: Topic :: Software Development :: Libraries :: Python Modules
Classifier: Programming Language :: Python :: 3
Classifier: License :: OSI Approved :: MIT License
Classifier: Operating System :: OS Independent
Requires-Python: >=3.6
Requires-Dist: tiktoken
Requires-Dist: colorama
Requires-Dist: PyGithub
